Metadata-Version: 2.1
Name: django-requests-loger
Version: 1.1.9
Summary: A Django application for logging and displaying HTTP requests.
Home-page: https://github.com/momin9/django-request-logs
Author: Momin Ali
Author-email: mominalikhoker589@gmail.com
License: MIT
Classifier: Programming Language :: Python :: 3
Classifier: License :: OSI Approved :: MIT License
Classifier: Operating System :: OS Independent
Classifier: Framework :: Django
Requires-Python: >=3.8
License-File: LICENSE
Requires-Dist: django >=4.2.14
Requires-Dist: django-environ
